mortuary.py
mortuary-0.1.1.dist-info/METADATA
mortuary-0.1.1.dist-info/WHEEL
mortuary-0.1.1.dist-info/licenses/LICENSE.txt
mortuary-0.1.1.dist-info/RECORD
