Metadata-Version: 2.1
Name: mortuary
Version: 0.1.1
Project-URL: Documentation, https://truemerrill.github.io/mortuary/
Project-URL: Issues, https://github.com/truemerrill/mortuary/issues
Project-URL: Source, https://github.com/truemerrill/mortuary
Author-email: True Merrill <true.merrill@gmail.com>
License-Expression: MIT
License-File: LICENSE.txt
Classifier: Development Status :: 4 - Beta
Classifier: Programming Language :: Python
Classifier: Programming Language :: Python :: 3.7
Classifier: Programming Language :: Python :: 3.8
Classifier: Programming Language :: Python :: 3.9
Classifier: Programming Language :: Python :: 3.10
Classifier: Programming Language :: Python :: 3.11
Classifier: Programming Language :: Python :: Implementation :: CPython
Classifier: Programming Language :: Python :: Implementation :: PyPy
Requires-Python: >=3.7
Provides-Extra: dev
Requires-Dist: mkdocs; extra == 'dev'
Requires-Dist: mkdocs-material; extra == 'dev'
Requires-Dist: mkdocstrings; extra == 'dev'
Requires-Dist: mkdocstrings-python; extra == 'dev'
Requires-Dist: pytest; extra == 'dev'
Provides-Extra: dill
Requires-Dist: dill; extra == 'dill'
Provides-Extra: ipdb
Requires-Dist: ipdb; extra == 'ipdb'
Provides-Extra: test
Requires-Dist: pytest; extra == 'test'
